odoo/addons/vertical_carsharing_mail/__init__.py
odoo/addons/vertical_carsharing_mail/__manifest__.py
odoo/addons/vertical_carsharing_mail/data/vc_mail_data.xml
odoo/addons/vertical_carsharing_mail/models/__init__.py
odoo/addons/vertical_carsharing_mail/models/account_invoice.py
odoo12_addon_vertical_carsharing_mail-12.0.0.0.3.dist-info/METADATA
odoo12_addon_vertical_carsharing_mail-12.0.0.0.3.dist-info/WHEEL
odoo12_addon_vertical_carsharing_mail-12.0.0.0.3.dist-info/top_level.txt
odoo12_addon_vertical_carsharing_mail-12.0.0.0.3.dist-info/RECORD
