Metadata-Version: 2.1
Name: odoo12-addon-vertical-carsharing-mail
Version: 12.0.0.0.3
Summary: Modules to manage mail templates
Home-page: https://www.sommobilitat.coop
Author: Som Mobilitat
License: UNKNOWN
Platform: UNKNOWN
Classifier: Programming Language :: Python
Classifier: Framework :: Odoo
Requires-Python: >=3.5
Requires-Dist: odoo (<12.1dev,>=12.0a)
